str2speech/__init__.py
str2speech/bark_tts.py
str2speech/base_tts.py
str2speech/cloner.py
str2speech/dia_tts.py
str2speech/kokoro_tts.py
str2speech/main.py
str2speech/mega3_tts.py
str2speech/mms_tts.py
str2speech/sesame_g.py
str2speech/sesame_m.py
str2speech/sesame_tts.py
str2speech/spark_tts.py
str2speech/speaker.py
str2speech/speecht5_tts.py
str2speech/utils.py
str2speech/zonos_tts.py
str2speech/dia/__init__.py
str2speech/dia/audio.py
str2speech/dia/config.py
str2speech/dia/layers.py
str2speech/dia/model.py
str2speech/megatts3/__init__.py
str2speech/megatts3/tts/__init__.py
str2speech/megatts3/tts/frontend_function.py
str2speech/megatts3/tts/infer_cli.py
str2speech/megatts3/tts/modules/__init__.py
str2speech/megatts3/tts/modules/aligner/__init__.py
str2speech/megatts3/tts/modules/aligner/whisper_small.py
str2speech/megatts3/tts/modules/ar_dur/__init__.py
str2speech/megatts3/tts/modules/ar_dur/ar_dur_predictor.py
str2speech/megatts3/tts/modules/ar_dur/commons/__init__.py
str2speech/megatts3/tts/modules/ar_dur/commons/layers.py
str2speech/megatts3/tts/modules/ar_dur/commons/nar_tts_modules.py
str2speech/megatts3/tts/modules/ar_dur/commons/rel_transformer.py
str2speech/megatts3/tts/modules/ar_dur/commons/rot_transformer.py
str2speech/megatts3/tts/modules/ar_dur/commons/seq_utils.py
str2speech/megatts3/tts/modules/ar_dur/commons/transformer.py
str2speech/megatts3/tts/modules/llm_dit/__init__.py
str2speech/megatts3/tts/modules/llm_dit/cfm.py
str2speech/megatts3/tts/modules/llm_dit/dit.py
str2speech/megatts3/tts/modules/llm_dit/time_embedding.py
str2speech/megatts3/tts/modules/llm_dit/transformer.py
str2speech/megatts3/tts/modules/wavvae/__init__.py
str2speech/megatts3/tts/modules/wavvae/decoder/__init__.py
str2speech/megatts3/tts/modules/wavvae/decoder/diag_gaussian.py
str2speech/megatts3/tts/modules/wavvae/decoder/hifigan_modules.py
str2speech/megatts3/tts/modules/wavvae/decoder/seanet_encoder.py
str2speech/megatts3/tts/modules/wavvae/decoder/wavvae_v3.py
str2speech-0.4.4.dist-info/licenses/LICENSE
str2speech-0.4.4.dist-info/METADATA
str2speech-0.4.4.dist-info/WHEEL
str2speech-0.4.4.dist-info/entry_points.txt
str2speech-0.4.4.dist-info/top_level.txt
str2speech-0.4.4.dist-info/RECORD
