Metadata-Version: 2.4
Name: str2speech
Version: 0.4.4
Summary: A powerful, Transformer-based text-to-speech (TTS) tool.
Home-page: https://github.com/hathibelagal-dev/str2speech
Author: Ashraff Hathibelagal
Project-URL: Source, https://github.com/hathibelagal-dev/str2speech
Project-URL: Tracker, https://github.com/hathibelagal-dev/str2speech/issues
Keywords: ai text-to-speech speech-synthesis nlp transformer voice
Classifier: Development Status :: 4 - Beta
Classifier: Intended Audience :: Developers
Classifier: License :: OSI Approved :: GNU General Public License v3 (GPLv3)
Classifier: Programming Language :: Python :: 3.11
Classifier: Programming Language :: Python :: 3.12
Requires-Python: >=3.11
License-File: LICENSE
Requires-Dist: transformers==4.50.3
Requires-Dist: torch
Requires-Dist: torchvision
Requires-Dist: torchaudio
Requires-Dist: tokenizers
Requires-Dist: scipy>=1.13.1
Requires-Dist: accelerate
Requires-Dist: numpy==2.0.2
Requires-Dist: kokoro==0.9.4
Requires-Dist: soundfile
Requires-Dist: gitpython
Requires-Dist: moshi==0.2.4
Requires-Dist: torchtune
Requires-Dist: torchao
Requires-Dist: huggingface_hub==0.28.1
Requires-Dist: soxr==0.5.0.post1
Requires-Dist: einops==0.8.1
Requires-Dist: einx==0.3.0
Requires-Dist: requests
Requires-Dist: snac>=1.2.1
Requires-Dist: attrdict
Requires-Dist: librosa==0.10.2.post1
Requires-Dist: pydub==0.25.1
Requires-Dist: pyloudnorm==0.1.1
Requires-Dist: x-transformers==2.1.37
Requires-Dist: openai-whisper==20240930
Requires-Dist: inflect==7.5.0
Requires-Dist: argbind
Dynamic: author
Dynamic: classifier
Dynamic: description
Dynamic: description-content-type
Dynamic: home-page
Dynamic: keywords
Dynamic: license-file
Dynamic: project-url
Dynamic: requires-dist
Dynamic: requires-python
Dynamic: summary
